nonebot_plugin_nai3/__init__.py
nonebot_plugin_nai3/config.py
nonebot_plugin_nai3/utils.py
nonebot_plugin_nai3-0.1.10.dist-info/LICENSE
nonebot_plugin_nai3-0.1.10.dist-info/METADATA
nonebot_plugin_nai3-0.1.10.dist-info/WHEEL
nonebot_plugin_nai3-0.1.10.dist-info/RECORD
