Metadata-Version: 2.1
Name: nonebot-plugin-nai3
Version: 0.1.10
Summary: 通过 NovelAI 生成图片
License: MIT
Author: zhulinyv
Author-email: zhulinyv2005@outlook.com
Requires-Python: >=3.9,<4.0
Classifier: License :: OSI Approved :: MIT License
Classifier: Programming Language :: Python :: 3
Classifier: Programming Language :: Python :: 3.9
Classifier: Programming Language :: Python :: 3.10
Classifier: Programming Language :: Python :: 3.11
Requires-Dist: httpx (>=0.24.1,<0.25.0)
Requires-Dist: nonebot-adapter-onebot (>=2.2.3,<3.0.0)
Requires-Dist: nonebot-plugin-smms (>=0.1.0,<0.2.0)
Requires-Dist: nonebot2 (>=2.2.1,<3.0.0)
Requires-Dist: nudenet (>=3.0.8,<4.0.0)
Requires-Dist: ujson (>=5.9.0,<6.0.0)
